tnsaai/__init__.py
tnsaai/async_client.py
tnsaai/client.py
tnsaai/config.py
tnsaai/exceptions.py
tnsaai/http_client.py
tnsaai/models/__init__.py
tnsaai/models/base.py
tnsaai/models/chat.py
tnsaai/models/common.py
tnsaai/models/completion.py
tnsaai/models/streaming.py
tnsaai_client-1.0.1.dist-info/METADATA
tnsaai_client-1.0.1.dist-info/WHEEL
tnsaai_client-1.0.1.dist-info/top_level.txt
tnsaai_client-1.0.1.dist-info/RECORD
