Metadata-Version: 2.4
Name: tnsaai-client
Version: 1.0.1
Summary: A powerful, OpenAI-compatible Python SDK for TNSA NGen3 Pro and Lite Models
Home-page: https://www.tnsaai.com
Author: TNSA AI
Author-email: TNSA AI <info@tnsaai.com>
License: MIT
Project-URL: Homepage, https://www.tnsaai.com
Project-URL: Documentation, https://docs.tnsaai.com
Project-URL: Repository, https://github.com/tnsaai/tnsaai-python
Project-URL: Bug Tracker, https://github.com/tnsaai/tnsaai-python/issues
Keywords: ai,api,tnsa,ngen3,llm,chat,completion
Classifier: Development Status :: 5 - Production/Stable
Classifier: Intended Audience :: Developers
Classifier: License :: OSI Approved :: MIT License
Classifier: Operating System :: OS Independent
Classifier: Programming Language :: Python :: 3
Classifier: Programming Language :: Python :: 3.8
Classifier: Programming Language :: Python :: 3.9
Classifier: Programming Language :: Python :: 3.10
Classifier: Programming Language :: Python :: 3.11
Classifier: Programming Language :: Python :: 3.12
Classifier: Topic :: Software Development :: Libraries :: Python Modules
Classifier: Topic :: Scientific/Engineering :: Artificial Intelligence
Requires-Python: >=3.8
Requires-Dist: requests>=2.25.0
Requires-Dist: aiohttp>=3.8.0
Requires-Dist: pydantic>=2.0.0
Requires-Dist: pyyaml>=6.0
Requires-Dist: typing-extensions>=4.0.0
Dynamic: author
Dynamic: home-page
Dynamic: requires-python
